prevectorchunks_web/__init__.py
prevectorchunks_web/api/__init__.py
prevectorchunks_web/api/views.py
prevectorchunks_web-0.1.1.dist-info/METADATA
prevectorchunks_web-0.1.1.dist-info/WHEEL
prevectorchunks_web-0.1.1.dist-info/top_level.txt
prevectorchunks_web-0.1.1.dist-info/RECORD
