Metadata-Version: 2.4
Name: prevectorchunks-web
Version: 0.1.1
Summary: A Python Django based REST endpoints that allows to convert a document into chunks to be inserted into pinecone vector database
Author-email: Zul Al-Kabir <zul.developer.2023@gmail.com>
Project-URL: Homepage, https://github.com/yourusername/mydep
Requires-Dist: Django==5.1
Requires-Dist: django-cors-headers~=4.4.0
Requires-Dist: fastapi~=0.112.2
Requires-Dist: PyJWT~=2.7.0
Requires-Dist: prevectorchunks_core==0.1.1
